{"image_id": 373, "file_name": "X51006557210.jpg", "width": 888, "height": 1939, "annotations": [{"bbox": [25, 74, 563, 23], "category_id": 0}, {"bbox": [167, 98, 272, 23], "category_id": 0}, {"bbox": [153, 122, 300, 23], "category_id": 0}, {"bbox": [116, 144, 184, 21], "category_id": 0}, {"bbox": [186, 166, 240, 22], "category_id": 0}, {"bbox": [131, 209, 349, 36], "category_id": 0}, {"bbox": [240, 266, 266, 35], "category_id": 0}, {"bbox": [21, 308, 85, 21], "category_id": 0}, {"bbox": [315, 308, 196, 22], "category_id": 0}, {"bbox": [17, 336, 354, 37], "category_id": 0}, {"bbox": [22, 379, 288, 22], "category_id": 0}, {"bbox": [22, 403, 176, 21], "category_id": 0}, {"bbox": [22, 425, 327, 21], "category_id": 0}, {"bbox": [22, 445, 204, 23], "category_id": 0}, {"bbox": [246, 468, 162, 21], "category_id": 0}, {"bbox": [16, 499, 135, 20], "category_id": 0}, {"bbox": [18, 535, 119, 22], "category_id": 0}, {"bbox": [17, 560, 111, 21], "category_id": 0}, {"bbox": [19, 583, 110, 21], "category_id": 0}, {"bbox": [180, 613, 217, 43], "category_id": 0}, {"bbox": [443, 615, 65, 35], "category_id": 0}, {"bbox": [18, 664, 122, 20], "category_id": 0}, {"bbox": [19, 687, 121, 22], "category_id": 0}, {"bbox": [40, 718, 356, 43], "category_id": 0}, {"bbox": [442, 719, 65, 35], "category_id": 0}, {"bbox": [348, 767, 49, 34], "category_id": 0}, {"bbox": [454, 767, 51, 34], "category_id": 0}, {"bbox": [52, 816, 344, 41], "category_id": 0}, {"bbox": [443, 818, 62, 34], "category_id": 0}, {"bbox": [182, 861, 215, 45], "category_id": 0}, {"bbox": [443, 864, 65, 35], "category_id": 0}, {"bbox": [230, 914, 167, 41], "category_id": 0}, {"bbox": [443, 915, 63, 34], "category_id": 1}, {"bbox": [23, 978, 96, 21], "category_id": 0}, {"bbox": [23, 1001, 534, 23], "category_id": 0}, {"bbox": [22, 1025, 467, 22], "category_id": 0}, {"bbox": [23, 1049, 534, 22], "category_id": 0}, {"bbox": [25, 1072, 441, 24], "category_id": 0}, {"bbox": [22, 1096, 472, 22], "category_id": 0}, {"bbox": [23, 1121, 182, 21], "category_id": 0}, {"bbox": [189, 1146, 239, 20], "category_id": 0}, {"bbox": [315, 144, 182, 21], "category_id": 0}, {"bbox": [429, 468, 58, 21], "category_id": 0}, {"bbox": [171, 497, 37, 20], "category_id": 0}, {"bbox": [218, 498, 37, 18], "category_id": 0}, {"bbox": [267, 498, 38, 19], "category_id": 0}, {"bbox": [325, 498, 14, 19], "category_id": 0}, {"bbox": [349, 498, 51, 19], "category_id": 0}, {"bbox": [418, 497, 87, 22], "category_id": 0}, {"bbox": [160, 537, 48, 18], "category_id": 0}, {"bbox": [242, 537, 14, 17], "category_id": 0}, {"bbox": [289, 537, 15, 17], "category_id": 0}, {"bbox": [325, 536, 14, 19], "category_id": 0}, {"bbox": [383, 536, 15, 19], "category_id": 0}, {"bbox": [443, 536, 63, 19], "category_id": 0}, {"bbox": [159, 561, 51, 18], "category_id": 0}, {"bbox": [242, 560, 15, 19], "category_id": 0}, {"bbox": [289, 560, 16, 19], "category_id": 0}, {"bbox": [324, 560, 16, 18], "category_id": 0}, {"bbox": [384, 560, 14, 19], "category_id": 0}, {"bbox": [454, 560, 51, 18], "category_id": 0}, {"bbox": [160, 584, 49, 19], "category_id": 0}, {"bbox": [245, 584, 13, 18], "category_id": 0}, {"bbox": [289, 583, 15, 19], "category_id": 0}, {"bbox": [325, 584, 15, 18], "category_id": 0}, {"bbox": [385, 583, 14, 20], "category_id": 0}, {"bbox": [453, 582, 51, 21], "category_id": 0}, {"bbox": [158, 665, 51, 18], "category_id": 0}, {"bbox": [231, 665, 26, 20], "category_id": 0}, {"bbox": [289, 664, 16, 21], "category_id": 0}, {"bbox": [325, 665, 15, 19], "category_id": 0}, {"bbox": [372, 663, 26, 21], "category_id": 0}, {"bbox": [443, 665, 62, 18], "category_id": 0}, {"bbox": [160, 688, 52, 19], "category_id": 0}, {"bbox": [232, 688, 27, 18], "category_id": 0}, {"bbox": [289, 688, 16, 18], "category_id": 0}, {"bbox": [326, 688, 15, 19], "category_id": 0}, {"bbox": [375, 688, 24, 18], "category_id": 0}, {"bbox": [455, 687, 50, 18], "category_id": 0}]}