{"image_id": 424, "file_name": "X51006912974.jpg", "width": 1497, "height": 2544, "annotations": [{"bbox": [1416, 1838, 1336, 114], "category_id": 0}, {"bbox": [1839, 1937, 499, 75], "category_id": 0}, {"bbox": [1935, 2029, 321, 76], "category_id": 0}, {"bbox": [1520, 2092, 1147, 95], "category_id": 0}, {"bbox": [1654, 2186, 875, 84], "category_id": 0}, {"bbox": [1903, 2273, 382, 66], "category_id": 0}, {"bbox": [1373, 2351, 823, 82], "category_id": 0}, {"bbox": [1378, 2490, 119, 63], "category_id": 0}, {"bbox": [1839, 2475, 100, 75], "category_id": 0}, {"bbox": [2698, 2440, 139, 57], "category_id": 0}, {"bbox": [1379, 2560, 974, 81], "category_id": 0}, {"bbox": [1384, 2672, 151, 70], "category_id": 0}, {"bbox": [1849, 2666, 37, 62], "category_id": 0}, {"bbox": [1385, 2775, 949, 92], "category_id": 0}, {"bbox": [1390, 2894, 148, 65], "category_id": 0}, {"bbox": [1858, 2879, 28, 65], "category_id": 0}, {"bbox": [2681, 2628, 156, 63], "category_id": 0}, {"bbox": [2693, 2844, 153, 70], "category_id": 0}, {"bbox": [2320, 2996, 530, 73], "category_id": 0}, {"bbox": [2393, 3075, 467, 76], "category_id": 0}, {"bbox": [2427, 3159, 434, 73], "category_id": 0}, {"bbox": [1394, 3310, 406, 78], "category_id": 0}, {"bbox": [2643, 3279, 214, 54], "category_id": 0}, {"bbox": [1404, 3416, 170, 60], "category_id": 0}, {"bbox": [2707, 3369, 148, 62], "category_id": 1}, {"bbox": [2707, 3450, 153, 67], "category_id": 0}, {"bbox": [1407, 3491, 210, 79], "category_id": 0}, {"bbox": [1410, 3689, 339, 65], "category_id": 0}, {"bbox": [2158, 3674, 233, 56], "category_id": 0}, {"bbox": [2719, 3655, 151, 65], "category_id": 0}, {"bbox": [1416, 3792, 348, 56], "category_id": 0}, {"bbox": [2299, 3765, 90, 48], "category_id": 0}, {"bbox": [2773, 3746, 97, 56], "category_id": 0}, {"bbox": [1793, 3891, 703, 72], "category_id": 0}, {"bbox": [1676, 3966, 938, 85], "category_id": 0}, {"bbox": [1828, 4051, 631, 88], "category_id": 0}, {"bbox": [1796, 4135, 697, 81], "category_id": 0}, {"bbox": [1721, 4214, 853, 82], "category_id": 0}, {"bbox": [1771, 4301, 764, 81], "category_id": 0}]}