{"image_id": 400, "file_name": "X51006620176.jpg", "width": 816, "height": 2156, "annotations": [{"bbox": [176, 318, 533, 45], "category_id": 0}, {"bbox": [297, 372, 289, 40], "category_id": 0}, {"bbox": [125, 421, 623, 47], "category_id": 0}, {"bbox": [144, 474, 585, 44], "category_id": 0}, {"bbox": [160, 524, 576, 37], "category_id": 0}, {"bbox": [195, 570, 481, 45], "category_id": 0}, {"bbox": [369, 624, 156, 41], "category_id": 0}, {"bbox": [315, 673, 250, 40], "category_id": 0}, {"bbox": [64, 774, 344, 37], "category_id": 0}, {"bbox": [69, 823, 289, 37], "category_id": 0}, {"bbox": [70, 875, 250, 37], "category_id": 0}, {"bbox": [64, 969, 219, 53], "category_id": 0}, {"bbox": [778, 777, 51, 35], "category_id": 0}, {"bbox": [484, 875, 176, 40], "category_id": 0}, {"bbox": [632, 977, 193, 43], "category_id": 0}, {"bbox": [71, 1074, 345, 40], "category_id": 0}, {"bbox": [68, 1121, 82, 43], "category_id": 0}, {"bbox": [71, 1174, 117, 39], "category_id": 0}, {"bbox": [69, 1274, 479, 40], "category_id": 0}, {"bbox": [671, 1076, 154, 37], "category_id": 1}, {"bbox": [672, 1128, 154, 37], "category_id": 0}, {"bbox": [686, 1176, 137, 37], "category_id": 0}, {"bbox": [631, 1270, 137, 43], "category_id": 0}, {"bbox": [66, 1373, 460, 39], "category_id": 0}, {"bbox": [68, 1420, 631, 47], "category_id": 0}, {"bbox": [178, 1523, 520, 39], "category_id": 0}, {"bbox": [254, 1567, 375, 47], "category_id": 0}, {"bbox": [217, 1619, 463, 45], "category_id": 0}, {"bbox": [692, 876, 96, 39], "category_id": 0}, {"bbox": [575, 1374, 253, 39], "category_id": 0}]}