{"image_id": 334, "file_name": "X51006556596.jpg", "width": 566, "height": 1093, "annotations": [{"bbox": [36, 117, 551, 23], "category_id": 0}, {"bbox": [174, 140, 275, 25], "category_id": 0}, {"bbox": [163, 165, 298, 22], "category_id": 0}, {"bbox": [124, 188, 183, 19], "category_id": 0}, {"bbox": [323, 188, 183, 20], "category_id": 0}, {"bbox": [195, 210, 238, 22], "category_id": 0}, {"bbox": [138, 253, 347, 33], "category_id": 0}, {"bbox": [245, 310, 268, 32], "category_id": 0}, {"bbox": [29, 347, 82, 22], "category_id": 0}, {"bbox": [321, 351, 195, 20], "category_id": 0}, {"bbox": [26, 381, 348, 33], "category_id": 0}, {"bbox": [27, 422, 287, 23], "category_id": 0}, {"bbox": [30, 446, 176, 21], "category_id": 0}, {"bbox": [26, 467, 325, 22], "category_id": 0}, {"bbox": [194, 1190, 239, 20], "category_id": 0}, {"bbox": [27, 489, 247, 20], "category_id": 0}, {"bbox": [256, 512, 158, 19], "category_id": 0}, {"bbox": [439, 511, 54, 21], "category_id": 0}, {"bbox": [23, 538, 137, 22], "category_id": 0}, {"bbox": [236, 542, 38, 17], "category_id": 0}, {"bbox": [285, 541, 36, 19], "category_id": 0}, {"bbox": [331, 541, 38, 19], "category_id": 0}, {"bbox": [387, 541, 20, 18], "category_id": 0}, {"bbox": [416, 540, 47, 21], "category_id": 0}, {"bbox": [485, 541, 84, 20], "category_id": 0}, {"bbox": [25, 578, 118, 20], "category_id": 0}, {"bbox": [224, 579, 50, 19], "category_id": 0}, {"bbox": [307, 580, 16, 17], "category_id": 0}, {"bbox": [354, 578, 16, 20], "category_id": 0}, {"bbox": [390, 580, 15, 19], "category_id": 0}, {"bbox": [449, 579, 13, 20], "category_id": 0}, {"bbox": [520, 578, 50, 21], "category_id": 0}, {"bbox": [21, 602, 110, 20], "category_id": 0}, {"bbox": [226, 604, 48, 19], "category_id": 0}, {"bbox": [307, 604, 12, 18], "category_id": 0}, {"bbox": [353, 605, 16, 17], "category_id": 0}, {"bbox": [390, 603, 14, 20], "category_id": 0}, {"bbox": [446, 605, 15, 16], "category_id": 0}, {"bbox": [509, 602, 62, 20], "category_id": 0}, {"bbox": [22, 627, 111, 18], "category_id": 0}, {"bbox": [224, 627, 49, 19], "category_id": 0}, {"bbox": [309, 628, 14, 15], "category_id": 0}, {"bbox": [356, 626, 11, 20], "category_id": 0}, {"bbox": [389, 627, 14, 19], "category_id": 0}, {"bbox": [441, 626, 20, 20], "category_id": 0}, {"bbox": [509, 627, 62, 19], "category_id": 0}, {"bbox": [190, 657, 214, 41], "category_id": 0}, {"bbox": [450, 658, 63, 34], "category_id": 0}, {"bbox": [25, 706, 193, 21], "category_id": 0}, {"bbox": [225, 708, 50, 19], "category_id": 0}, {"bbox": [308, 709, 13, 16], "category_id": 0}, {"bbox": [356, 710, 14, 16], "category_id": 0}, {"bbox": [390, 709, 15, 19], "category_id": 0}, {"bbox": [449, 709, 14, 18], "category_id": 0}, {"bbox": [511, 708, 60, 21], "category_id": 0}, {"bbox": [24, 731, 111, 20], "category_id": 0}, {"bbox": [224, 731, 51, 20], "category_id": 0}, {"bbox": [298, 730, 23, 21], "category_id": 0}, {"bbox": [354, 732, 16, 19], "category_id": 0}, {"bbox": [391, 731, 13, 19], "category_id": 0}, {"bbox": [438, 732, 25, 17], "category_id": 0}, {"bbox": [509, 731, 63, 18], "category_id": 0}, {"bbox": [46, 759, 355, 45], "category_id": 0}, {"bbox": [450, 763, 61, 34], "category_id": 0}, {"bbox": [353, 811, 48, 34], "category_id": 0}, {"bbox": [464, 811, 45, 34], "category_id": 0}, {"bbox": [60, 859, 341, 43], "category_id": 0}, {"bbox": [449, 862, 65, 35], "category_id": 0}, {"bbox": [186, 907, 215, 38], "category_id": 0}, {"bbox": [449, 910, 60, 32], "category_id": 0}, {"bbox": [235, 958, 167, 41], "category_id": 0}, {"bbox": [447, 961, 65, 34], "category_id": 1}, {"bbox": [29, 1021, 95, 20], "category_id": 0}, {"bbox": [28, 1045, 533, 22], "category_id": 0}, {"bbox": [28, 1067, 465, 23], "category_id": 0}, {"bbox": [27, 1091, 535, 25], "category_id": 0}, {"bbox": [31, 1115, 439, 24], "category_id": 0}, {"bbox": [29, 1141, 465, 23], "category_id": 0}, {"bbox": [29, 1165, 181, 21], "category_id": 0}]}