{"image_id": 504, "file_name": "X51007339639.jpg", "width": 4961, "height": 7016, "annotations": [{"bbox": [75, 202, 424, 26], "category_id": 0}, {"bbox": [75, 229, 428, 27], "category_id": 0}, {"bbox": [125, 252, 328, 28], "category_id": 0}, {"bbox": [239, 279, 101, 20], "category_id": 0}, {"bbox": [118, 301, 342, 26], "category_id": 0}, {"bbox": [151, 326, 276, 28], "category_id": 0}, {"bbox": [104, 351, 367, 27], "category_id": 0}, {"bbox": [57, 375, 462, 28], "category_id": 0}, {"bbox": [157, 401, 254, 26], "category_id": 0}, {"bbox": [149, 454, 281, 43], "category_id": 0}, {"bbox": [32, 551, 56, 25], "category_id": 0}, {"bbox": [31, 600, 483, 23], "category_id": 0}, {"bbox": [34, 625, 242, 25], "category_id": 0}, {"bbox": [305, 624, 179, 25], "category_id": 0}, {"bbox": [32, 671, 56, 25], "category_id": 0}, {"bbox": [256, 673, 44, 25], "category_id": 0}, {"bbox": [354, 675, 45, 20], "category_id": 0}, {"bbox": [431, 676, 83, 20], "category_id": 0}, {"bbox": [344, 701, 51, 24], "category_id": 0}, {"bbox": [456, 701, 54, 25], "category_id": 0}, {"bbox": [35, 722, 165, 26], "category_id": 0}, {"bbox": [256, 725, 17, 23], "category_id": 0}, {"bbox": [345, 727, 56, 19], "category_id": 1}, {"bbox": [458, 727, 52, 23], "category_id": 1}, {"bbox": [519, 728, 15, 23], "category_id": 0}, {"bbox": [35, 748, 323, 32], "category_id": 0}, {"bbox": [32, 799, 177, 27], "category_id": 0}, {"bbox": [345, 802, 12, 20], "category_id": 0}, {"bbox": [222, 876, 194, 23], "category_id": 0}, {"bbox": [298, 901, 56, 22], "category_id": 0}, {"bbox": [298, 925, 107, 24], "category_id": 0}, {"bbox": [61, 947, 125, 24], "category_id": 0}, {"bbox": [60, 972, 104, 25], "category_id": 0}, {"bbox": [62, 997, 149, 30], "category_id": 0}, {"bbox": [487, 878, 52, 21], "category_id": 1}, {"bbox": [483, 900, 54, 23], "category_id": 0}, {"bbox": [485, 924, 53, 28], "category_id": 0}, {"bbox": [437, 950, 104, 24], "category_id": 1}, {"bbox": [412, 975, 127, 26], "category_id": 0}, {"bbox": [413, 996, 125, 28], "category_id": 0}, {"bbox": [116, 1045, 342, 32], "category_id": 0}, {"bbox": [214, 1096, 142, 30], "category_id": 0}, {"bbox": [39, 1145, 52, 28], "category_id": 0}, {"bbox": [239, 1147, 81, 28], "category_id": 0}, {"bbox": [373, 1149, 23, 25], "category_id": 0}, {"bbox": [443, 1150, 88, 24], "category_id": 0}, {"bbox": [40, 1195, 35, 26], "category_id": 0}, {"bbox": [264, 1197, 56, 25], "category_id": 0}, {"bbox": [376, 1202, 17, 20], "category_id": 0}, {"bbox": [477, 1196, 58, 27], "category_id": 0}, {"bbox": [281, 1270, 121, 27], "category_id": 0}, {"bbox": [477, 1272, 56, 24], "category_id": 0}, {"bbox": [98, 1375, 376, 25], "category_id": 0}, {"bbox": [126, 1400, 319, 27], "category_id": 0}, {"bbox": [65, 1427, 441, 22], "category_id": 0}, {"bbox": [39, 1448, 490, 25], "category_id": 0}, {"bbox": [52, 1475, 469, 23], "category_id": 0}, {"bbox": [148, 1494, 271, 23], "category_id": 0}]}