{"image_id": 19, "file_name": "X51005337872.jpg", "width": 560, "height": 875, "annotations": [{"bbox": [63, 340, 490, 29], "category_id": 0}, {"bbox": [246, 379, 99, 23], "category_id": 0}, {"bbox": [74, 406, 467, 26], "category_id": 0}, {"bbox": [196, 435, 221, 24], "category_id": 0}, {"bbox": [183, 474, 249, 23], "category_id": 0}, {"bbox": [30, 520, 105, 23], "category_id": 0}, {"bbox": [157, 522, 146, 22], "category_id": 0}, {"bbox": [362, 525, 82, 22], "category_id": 0}, {"bbox": [472, 527, 46, 23], "category_id": 0}, {"bbox": [29, 554, 87, 23], "category_id": 0}, {"bbox": [157, 556, 70, 21], "category_id": 0}, {"bbox": [364, 558, 59, 23], "category_id": 0}, {"bbox": [460, 561, 127, 21], "category_id": 0}, {"bbox": [30, 586, 145, 27], "category_id": 0}, {"bbox": [363, 589, 61, 23], "category_id": 0}, {"bbox": [461, 591, 98, 23], "category_id": 0}, {"bbox": [29, 639, 128, 26], "category_id": 0}, {"bbox": [336, 643, 38, 24], "category_id": 0}, {"bbox": [418, 644, 57, 22], "category_id": 0}, {"bbox": [492, 644, 89, 25], "category_id": 0}, {"bbox": [27, 669, 232, 24], "category_id": 0}, {"bbox": [337, 674, 34, 21], "category_id": 0}, {"bbox": [428, 674, 47, 21], "category_id": 0}, {"bbox": [523, 676, 57, 21], "category_id": 0}, {"bbox": [29, 694, 217, 24], "category_id": 0}, {"bbox": [154, 729, 100, 23], "category_id": 0}, {"bbox": [337, 732, 34, 21], "category_id": 0}, {"bbox": [418, 734, 58, 20], "category_id": 0}, {"bbox": [525, 735, 55, 21], "category_id": 0}, {"bbox": [29, 754, 73, 21], "category_id": 0}, {"bbox": [27, 788, 222, 23], "category_id": 0}, {"bbox": [339, 792, 33, 21], "category_id": 0}, {"bbox": [416, 792, 58, 21], "category_id": 0}, {"bbox": [522, 795, 58, 19], "category_id": 0}, {"bbox": [28, 813, 115, 21], "category_id": 0}, {"bbox": [27, 846, 250, 23], "category_id": 0}, {"bbox": [337, 848, 32, 22], "category_id": 0}, {"bbox": [426, 850, 48, 20], "category_id": 0}, {"bbox": [534, 850, 46, 21], "category_id": 0}, {"bbox": [28, 870, 110, 26], "category_id": 0}, {"bbox": [27, 905, 234, 21], "category_id": 0}, {"bbox": [338, 907, 33, 20], "category_id": 0}, {"bbox": [417, 909, 57, 19], "category_id": 0}, {"bbox": [524, 909, 56, 20], "category_id": 0}, {"bbox": [27, 928, 248, 21], "category_id": 0}, {"bbox": [164, 965, 108, 27], "category_id": 0}, {"bbox": [345, 968, 17, 20], "category_id": 0}, {"bbox": [516, 962, 62, 22], "category_id": 0}, {"bbox": [165, 1029, 301, 26], "category_id": 0}, {"bbox": [523, 1033, 58, 20], "category_id": 0}, {"bbox": [342, 1070, 122, 23], "category_id": 0}, {"bbox": [529, 1072, 50, 23], "category_id": 0}, {"bbox": [342, 1107, 124, 24], "category_id": 0}, {"bbox": [535, 1110, 44, 22], "category_id": 0}, {"bbox": [333, 1147, 133, 27], "category_id": 0}, {"bbox": [528, 1151, 52, 21], "category_id": 0}, {"bbox": [116, 1184, 345, 31], "category_id": 0}, {"bbox": [505, 1189, 75, 25], "category_id": 1}, {"bbox": [27, 729, 10, 25], "category_id": 0}]}