{"image_id": 222, "file_name": "X51006008091.jpg", "width": 661, "height": 1549, "annotations": [{"bbox": [144, 95, 421, 49], "category_id": 0}, {"bbox": [108, 154, 530, 59], "category_id": 0}, {"bbox": [197, 219, 317, 34], "category_id": 0}, {"bbox": [124, 260, 460, 32], "category_id": 0}, {"bbox": [52, 300, 605, 30], "category_id": 0}, {"bbox": [107, 338, 497, 32], "category_id": 0}, {"bbox": [142, 380, 411, 28], "category_id": 0}, {"bbox": [215, 459, 299, 29], "category_id": 0}, {"bbox": [38, 539, 248, 30], "category_id": 0}, {"bbox": [39, 579, 124, 31], "category_id": 0}, {"bbox": [337, 538, 358, 30], "category_id": 0}, {"bbox": [392, 580, 230, 28], "category_id": 0}, {"bbox": [73, 658, 514, 30], "category_id": 0}, {"bbox": [128, 697, 370, 31], "category_id": 0}, {"bbox": [39, 777, 193, 29], "category_id": 0}, {"bbox": [533, 778, 105, 29], "category_id": 0}, {"bbox": [38, 856, 320, 30], "category_id": 0}, {"bbox": [93, 896, 174, 30], "category_id": 0}, {"bbox": [58, 935, 262, 31], "category_id": 0}, {"bbox": [574, 897, 123, 29], "category_id": 0}, {"bbox": [570, 937, 90, 30], "category_id": 0}, {"bbox": [39, 1015, 373, 28], "category_id": 0}, {"bbox": [40, 1053, 70, 30], "category_id": 0}, {"bbox": [41, 1094, 106, 28], "category_id": 0}, {"bbox": [590, 1015, 69, 29], "category_id": 1}, {"bbox": [553, 1056, 108, 30], "category_id": 0}, {"bbox": [574, 1094, 87, 32], "category_id": 0}, {"bbox": [41, 1171, 170, 33], "category_id": 0}, {"bbox": [36, 1213, 195, 31], "category_id": 0}, {"bbox": [36, 1252, 111, 34], "category_id": 0}, {"bbox": [268, 1214, 192, 29], "category_id": 0}, {"bbox": [642, 1173, 19, 30], "category_id": 0}, {"bbox": [516, 1212, 142, 33], "category_id": 0}, {"bbox": [392, 1254, 70, 31], "category_id": 0}, {"bbox": [590, 1253, 69, 31], "category_id": 0}, {"bbox": [37, 1331, 229, 34], "category_id": 0}, {"bbox": [569, 1333, 91, 31], "category_id": 0}, {"bbox": [144, 1414, 428, 30], "category_id": 0}, {"bbox": [124, 1454, 483, 29], "category_id": 0}, {"bbox": [107, 1493, 509, 32], "category_id": 0}, {"bbox": [197, 1534, 319, 32], "category_id": 0}, {"bbox": [146, 1574, 425, 30], "category_id": 0}, {"bbox": [144, 1614, 428, 30], "category_id": 0}]}