{"image_id": 252, "file_name": "X51006387813.jpg", "width": 740, "height": 2465, "annotations": [{"bbox": [132, 241, 366, 30], "category_id": 0}, {"bbox": [174, 277, 295, 29], "category_id": 0}, {"bbox": [242, 313, 144, 28], "category_id": 0}, {"bbox": [115, 347, 383, 30], "category_id": 0}, {"bbox": [200, 380, 224, 29], "category_id": 0}, {"bbox": [93, 414, 432, 32], "category_id": 0}, {"bbox": [173, 452, 280, 27], "category_id": 0}, {"bbox": [253, 486, 128, 26], "category_id": 0}, {"bbox": [130, 520, 368, 29], "category_id": 0}, {"bbox": [145, 587, 310, 33], "category_id": 0}, {"bbox": [29, 658, 227, 54], "category_id": 0}, {"bbox": [423, 636, 226, 60], "category_id": 0}, {"bbox": [30, 714, 200, 27], "category_id": 0}, {"bbox": [30, 746, 271, 30], "category_id": 0}, {"bbox": [411, 747, 130, 30], "category_id": 0}, {"bbox": [30, 783, 59, 30], "category_id": 0}, {"bbox": [130, 783, 296, 28], "category_id": 0}, {"bbox": [115, 2405, 383, 30], "category_id": 0}, {"bbox": [29, 817, 201, 29], "category_id": 0}, {"bbox": [29, 886, 160, 33], "category_id": 0}, {"bbox": [240, 886, 47, 33], "category_id": 0}, {"bbox": [340, 885, 100, 32], "category_id": 0}, {"bbox": [468, 884, 70, 32], "category_id": 0}, {"bbox": [553, 885, 44, 29], "category_id": 0}, {"bbox": [32, 956, 299, 31], "category_id": 0}, {"bbox": [26, 1024, 418, 30], "category_id": 0}, {"bbox": [32, 1096, 353, 30], "category_id": 0}, {"bbox": [31, 1164, 268, 28], "category_id": 0}, {"bbox": [230, 994, 43, 25], "category_id": 0}, {"bbox": [231, 1059, 41, 28], "category_id": 0}, {"bbox": [231, 1131, 40, 25], "category_id": 0}, {"bbox": [230, 1200, 41, 25], "category_id": 0}, {"bbox": [341, 992, 74, 26], "category_id": 0}, {"bbox": [340, 1059, 73, 29], "category_id": 0}, {"bbox": [344, 1130, 69, 26], "category_id": 0}, {"bbox": [341, 1197, 70, 29], "category_id": 0}, {"bbox": [465, 991, 74, 30], "category_id": 0}, {"bbox": [466, 1059, 74, 27], "category_id": 0}, {"bbox": [470, 1128, 69, 29], "category_id": 0}, {"bbox": [466, 1199, 73, 27], "category_id": 0}, {"bbox": [567, 992, 29, 28], "category_id": 0}, {"bbox": [567, 1060, 30, 28], "category_id": 0}, {"bbox": [565, 1129, 31, 30], "category_id": 0}, {"bbox": [567, 1197, 29, 29], "category_id": 0}, {"bbox": [31, 1263, 310, 34], "category_id": 0}, {"bbox": [29, 1300, 269, 30], "category_id": 0}, {"bbox": [29, 1332, 171, 32], "category_id": 0}, {"bbox": [33, 1369, 352, 30], "category_id": 0}, {"bbox": [522, 1262, 76, 32], "category_id": 0}, {"bbox": [536, 1298, 61, 31], "category_id": 0}, {"bbox": [536, 1334, 59, 28], "category_id": 0}, {"bbox": [511, 1370, 84, 28], "category_id": 1}, {"bbox": [31, 1439, 161, 53], "category_id": 0}, {"bbox": [429, 1440, 165, 49], "category_id": 1}, {"bbox": [30, 1526, 171, 28], "category_id": 0}, {"bbox": [297, 1525, 143, 30], "category_id": 0}, {"bbox": [480, 1529, 116, 28], "category_id": 0}, {"bbox": [30, 1560, 186, 32], "category_id": 0}, {"bbox": [32, 1665, 56, 27], "category_id": 0}, {"bbox": [511, 1667, 81, 26], "category_id": 1}, {"bbox": [23, 1693, 261, 35], "category_id": 0}, {"bbox": [26, 1732, 221, 31], "category_id": 0}, {"bbox": [27, 1768, 89, 27], "category_id": 0}, {"bbox": [28, 1904, 159, 32], "category_id": 0}, {"bbox": [310, 1905, 143, 33], "category_id": 0}, {"bbox": [493, 1905, 100, 32], "category_id": 0}, {"bbox": [29, 1937, 33, 28], "category_id": 0}, {"bbox": [171, 1938, 83, 32], "category_id": 0}, {"bbox": [368, 1938, 88, 32], "category_id": 0}, {"bbox": [535, 1942, 58, 28], "category_id": 0}, {"bbox": [198, 2104, 239, 32], "category_id": 0}, {"bbox": [238, 2308, 133, 32], "category_id": 0}, {"bbox": [196, 2341, 245, 33], "category_id": 0}]}