{"image_id": 145, "file_name": "X51005711454.jpg", "width": 831, "height": 1892, "annotations": [{"bbox": [188, 139, 542, 57], "category_id": 0}, {"bbox": [341, 196, 212, 41], "category_id": 0}, {"bbox": [235, 240, 436, 54], "category_id": 0}, {"bbox": [240, 294, 428, 46], "category_id": 0}, {"bbox": [83, 343, 730, 54], "category_id": 0}, {"bbox": [317, 441, 227, 52], "category_id": 0}, {"bbox": [132, 534, 611, 54], "category_id": 0}, {"bbox": [34, 586, 219, 46], "category_id": 0}, {"bbox": [619, 591, 227, 46], "category_id": 0}, {"bbox": [28, 678, 219, 52], "category_id": 0}, {"bbox": [235, 733, 444, 46], "category_id": 0}, {"bbox": [34, 782, 382, 88], "category_id": 0}, {"bbox": [31, 903, 441, 49], "category_id": 0}, {"bbox": [676, 908, 129, 46], "category_id": 0}, {"bbox": [23, 957, 565, 46], "category_id": 0}, {"bbox": [658, 962, 152, 44], "category_id": 0}, {"bbox": [41, 1011, 472, 41], "category_id": 0}, {"bbox": [678, 1011, 134, 39], "category_id": 0}, {"bbox": [41, 1060, 400, 41], "category_id": 0}, {"bbox": [678, 1060, 124, 41], "category_id": 0}, {"bbox": [41, 1109, 346, 44], "category_id": 0}, {"bbox": [673, 1109, 137, 41], "category_id": 0}, {"bbox": [95, 1158, 98, 39], "category_id": 0}, {"bbox": [655, 1161, 116, 39], "category_id": 0}, {"bbox": [658, 1259, 108, 39], "category_id": 0}, {"bbox": [103, 1303, 157, 49], "category_id": 0}, {"bbox": [658, 1310, 101, 39], "category_id": 0}, {"bbox": [101, 1357, 222, 46], "category_id": 0}, {"bbox": [671, 1357, 93, 39], "category_id": 0}, {"bbox": [95, 1403, 139, 39], "category_id": 0}, {"bbox": [673, 1401, 88, 46], "category_id": 0}, {"bbox": [90, 1450, 137, 46], "category_id": 0}, {"bbox": [655, 1450, 108, 41], "category_id": 1}, {"bbox": [95, 1499, 163, 44], "category_id": 0}, {"bbox": [673, 1504, 93, 46], "category_id": 0}, {"bbox": [88, 1545, 235, 46], "category_id": 0}, {"bbox": [642, 1548, 119, 44], "category_id": 0}, {"bbox": [95, 1597, 152, 49], "category_id": 0}, {"bbox": [655, 1599, 114, 44], "category_id": 0}, {"bbox": [98, 1648, 199, 39], "category_id": 0}, {"bbox": [668, 1648, 93, 46], "category_id": 0}, {"bbox": [119, 1695, 660, 49], "category_id": 0}, {"bbox": [160, 1749, 588, 44], "category_id": 0}, {"bbox": [204, 1790, 469, 46], "category_id": 0}, {"bbox": [90, 1888, 219, 49], "category_id": 0}, {"bbox": [338, 1883, 204, 46], "category_id": 0}, {"bbox": [568, 1886, 144, 52], "category_id": 0}, {"bbox": [95, 1937, 204, 44], "category_id": 0}, {"bbox": [330, 1937, 116, 49], "category_id": 0}, {"bbox": [573, 1937, 95, 49], "category_id": 0}, {"bbox": [97, 1984, 204, 42], "category_id": 0}, {"bbox": [328, 1979, 108, 52], "category_id": 0}, {"bbox": [570, 1989, 95, 39], "category_id": 0}, {"bbox": [712, 689, 142, 41], "category_id": 0}]}