{"form": [{"bbox": [[63, 340], [553, 369]], "text": ["SYL ROASTED DELIGHTS SDN. BHD."], "label": "other"}, {"bbox": [[246, 379], [345, 402]], "text": ["1227039"], "label": "other"}, {"bbox": [[74, 406], [541, 432]], "text": ["75", " JALAN SS 22/19", " DAMANSARA JAYA", " 47400 PJ", ""], "label": "other"}, {"bbox": [[196, 435], [417, 459]], "text": ["TEL : 03-7731 8169"], "label": "other"}, {"bbox": [[183, 474], [432, 497]], "text": ["GST ID : 002046390272"], "label": "other"}, {"bbox": [[30, 520], [135, 543]], "text": ["DOC NO. :"], "label": "other"}, {"bbox": [[157, 522], [303, 544]], "text": ["SO00022185"], "label": "other"}, {"bbox": [[362, 525], [444, 547]], "text": ["TABLE"], "label": "other"}, {"bbox": [[472, 527], [518, 550]], "text": ["A10"], "label": "other"}, {"bbox": [[29, 554], [116, 577]], "text": ["CASHIER"], "label": "other"}, {"bbox": [[157, 556], [227, 577]], "text": ["USER"], "label": "other"}, {"bbox": [[364, 558], [423, 581]], "text": ["DATE:"], "label": "other"}, {"bbox": [[460, 561], [587, 582]], "text": ["06/03/2018"], "label": "other"}, {"bbox": [[30, 586], [175, 613]], "text": ["SALESPERSON:"], "label": "other"}, {"bbox": [[363, 589], [424, 612]], "text": ["TIME:"], "label": "other"}, {"bbox": [[461, 591], [559, 614]], "text": ["12:06:00"], "label": "other"}, {"bbox": [[29, 639], [157, 665]], "text": ["DESCRIPTION"], "label": "other"}, {"bbox": [[336, 643], [374, 667]], "text": ["QTY"], "label": "other"}, {"bbox": [[418, 644], [475, 666]], "text": ["PRICE"], "label": "other"}, {"bbox": [[492, 644], [581, 669]], "text": ["AMOUNT"], "label": "other"}, {"bbox": [[27, 669], [259, 693]], "text": ["(T02) BRAISED PORK"], "label": "other"}, {"bbox": [[337, 674], [371, 695]], "text": ["2.0"], "label": "other"}, {"bbox": [[428, 674], [475, 695]], "text": ["7.00"], "label": "other"}, {"bbox": [[523, 676], [580, 697]], "text": ["14.00"], "label": "other"}, {"bbox": [[29, 694], [246, 718]], "text": ["RICE WITH PEANUT"], "label": "other"}, {"bbox": [[154, 729], [254, 752]], "text": ["T PORK -"], "label": "other"}, {"bbox": [[337, 732], [371, 753]], "text": ["1.0"], "label": "other"}, {"bbox": [[418, 734], [476, 754]], "text": ["12.00"], "label": "other"}, {"bbox": [[525, 735], [580, 756]], "text": ["12.00"], "label": "other"}, {"bbox": [[29, 754], [102, 775]], "text": ["SMALL"], "label": "other"}, {"bbox": [[27, 788], [249, 811]], "text": ["(V02) SOUR & SPICY"], "label": "other"}, {"bbox": [[339, 792], [372, 813]], "text": ["1.0"], "label": "other"}, {"bbox": [[416, 792], [474, 813]], "text": ["12.00"], "label": "other"}, {"bbox": [[522, 795], [580, 814]], "text": ["12.00"], "label": "other"}, {"bbox": [[28, 813], [143, 834]], "text": ["MUSTARD"], "label": "other"}, {"bbox": [[27, 846], [277, 869]], "text": ["(B03) JASMINE GREEN"], "label": "other"}, {"bbox": [[337, 848], [369, 870]], "text": ["2.0"], "label": "other"}, {"bbox": [[426, 850], [474, 870]], "text": ["2.30"], "label": "other"}, {"bbox": [[534, 850], [580, 871]], "text": ["4.60"], "label": "other"}, {"bbox": [[28, 870], [138, 896]], "text": ["TEA(HOT)"], "label": "other"}, {"bbox": [[27, 905], [261, 926]], "text": ["(R05) ROAST PORK +"], "label": "other"}, {"bbox": [[338, 907], [371, 927]], "text": ["1.0"], "label": "other"}, {"bbox": [[417, 909], [474, 928]], "text": ["11.90"], "label": "other"}, {"bbox": [[524, 909], [580, 929]], "text": ["11.90"], "label": "other"}, {"bbox": [[27, 928], [275, 949]], "text": ["ROAST CHICKEN RICE"], "label": "other"}, {"bbox": [[164, 965], [272, 992]], "text": ["TOTAL QTY:"], "label": "other"}, {"bbox": [[345, 968], [362, 988]], "text": ["7"], "label": "other"}, {"bbox": [[516, 962], [578, 984]], "text": ["51.42"], "label": "other"}, {"bbox": [[165, 1029], [466, 1055]], "text": ["TOTAL SALES (EXCLUDING GST) :"], "label": "other"}, {"bbox": [[523, 1033], [581, 1053]], "text": ["51.42"], "label": "other"}, {"bbox": [[342, 1070], [464, 1093]], "text": ["DISCOUNT :"], "label": "other"}, {"bbox": [[529, 1072], [579, 1095]], "text": ["0.00"], "label": "other"}, {"bbox": [[342, 1107], [466, 1131]], "text": ["TOTAL GST :"], "label": "other"}, {"bbox": [[535, 1110], [579, 1132]], "text": ["3.08"], "label": "other"}, {"bbox": [[333, 1147], [466, 1174]], "text": ["ROUNDING :"], "label": "other"}, {"bbox": [[528, 1151], [580, 1172]], "text": ["0.00"], "label": "other"}, {"bbox": [[116, 1184], [461, 1215]], "text": ["TOTAL SALES (INCLUSIVE OF GST)"], "label": "other"}, {"bbox": [[505, 1189], [580, 1214]], "text": ["54.50"], "label": "total"}, {"bbox": [[27, 729], [37, 754]], "text": ["("], "label": "other"}]}